quart_wtf/__init__.py
quart_wtf/const.py
quart_wtf/csrf.py
quart_wtf/file.py
quart_wtf/form.py
quart_wtf/meta.py
quart_wtf/utils.py
quart_wtf-0.0.1.dist-info/WHEEL
quart_wtf-0.0.1.dist-info/METADATA
quart_wtf-0.0.1.dist-info/RECORD
